magnesium/__init__.py
magnesium/extractor/__init__.py
magnesium/extractor/base_extractor.py
magnesium/extractor/xpath_extractor.py
magnesium/mapping/__init__.py
magnesium/mapping/base_mapping.py
magnesium/mapping/simple_mapping.py
magnesium/node/__init__.py
magnesium/node/attribute.py
magnesium/node/tag.py
magnesium/path_interpreter/__init__.py
magnesium/path_interpreter/base_path_interpreter.py
magnesium/path_interpreter/xpath_interpreter.py
magnesium/path_processor/__init__.py
magnesium/path_processor/base_path_processor.py
magnesium/path_processor/simple_path_processor.py
magnesium/pipeline/__init__.py
magnesium/pipeline/base_pipeline_builder.py
magnesium/pipeline/extractor_pipeline_builder.py
magnesium/pipeline/pipeline.py
magnesium/pipeline/pipeline_step.py
magnesium/pipeline/schema_pipeline_builder.py
magnesium/post_processor/__init__.py
magnesium/post_processor/base_post_processor.py
magnesium/post_processor/list_of_dicts_processor.py
magnesium/post_processor/pandas_data_frame_processor.py
magnesium/post_processor/space_normalizer_processor.py
magnesium/post_processor/tail_cutter_processor.py
magnesium/prefab/__init__.py
magnesium/prefab/base_prefab.py
magnesium/prefab/list_of_dicts_prefab.py
magnesium/prefab/pandas_prefab.py
magnesium/query_marker/__init__.py
magnesium/query_marker/base_query_marker_strategy.py
magnesium/query_marker/double_curly_query_marker_strategy.py
magnesium/query_path/__init__.py
magnesium/query_path/query_path.py
magnesium/utils/__init__.py
magnesium/utils/snapshootable_stack.py
Magnesium-0.1.1.dist-info/LICENSE
Magnesium-0.1.1.dist-info/METADATA
Magnesium-0.1.1.dist-info/WHEEL
Magnesium-0.1.1.dist-info/top_level.txt
Magnesium-0.1.1.dist-info/RECORD
